<?xml version="1.0" encoding="UTF-8"?>
<court xmlns:xsi="http://www.w3.org/2001/XMLSchema-instance" creator="http://courtlabs.org" created="2012-04-16T11:11:33" modified="2013-08-07T09:26:58" license="http://creativecommons.org/licenses/by-nc-sa/3.0/us/">
  <courtName id="marshall/mars4">Marshall Court (1807-1810)</courtName>
  <courtJustice id="john_marshall">John Marshall</courtJustice>
  <courtJustice id="william_cushing">William Cushing</courtJustice>
  <courtJustice id="samuel_chase">Samuel Chase</courtJustice>
  <courtJustice id="bushrod_washington">Bushrod Washington</courtJustice>
  <courtJustice id="william_johnson">William Johnson</courtJustice>
  <courtJustice id="brockholst_livingston">Brockholst Livingston</courtJustice>
  <courtJustice id="thomas_todd">Thomas Todd</courtJustice>
  <courtDefined>Thomas Todd Joined</courtDefined>
  <courtStartDate formatted="Monday, May 4, 1807">1807-05-04</courtStartDate>
  <courtEndDate formatted="Thursday, September 13, 1810">1810-09-13</courtEndDate>
</court>
